<?xml version="1.0" encoding="UTF-8"?>
<addon
  id="webinterface.arc"
  version="0.1.0"
  name="Arc"
  provider-name="moi">
  <requires>
    <import addon="xbmc.json" version="6.0.0" />
  </requires>
  <extension
    point="xbmc.gui.webinterface"/>
  <extension point="xbmc.addon.metadata">
    <summary lang="en">Arc Dev</summary>
    <description lang="en">Only use this version for dev, see dist folder for production ready</description>
    <platform>all</platform>
    <language>en</language>
  </extension>
</addon>